{
    "status": true, 
    "model": {
        "tagAncestry": [], 
        "solved_count": 45696, 
        "can_solve": true, 
        "dynamic": true, 
        "epoch_starttime": null, 
        "difficulty_name": "Easy", 
        "compile_and_test": true, 
        "submit_disabled": false, 
        "company_id": null, 
        "languages": [
            "cpp", 
            "cpp14", 
            "java", 
            "javascript", 
            "python", 
            "python3"
        ], 
        "leaderboard_out_of_sync_message": null, 
        "primary_contest": null, 
        "factor": 5, 
        "default_language": null, 
        "moderator_or_support": false, 
        "leaderboard_out_of_sync": null, 
        "contest_slug": "master", 
        "python3_template": "#Body\n\"\"\"\n Get Node data of the Nth Node from the end.\n head could be None as well for empty list\n Node is defined as\n \n class Node(object):\n \n   def __init__(self, data=None, next_node=None):\n       self.data = data\n       self.next = next_node\n\n return back the node data of the linked list in the below method.\n\"\"\"\n\ndef GetNode(head, position):\n  \n  \n  \n  \n  \n  \n  \n  \n  ", 
        "name": "Get Node Value", 
        "level": 16, 
        "success_ratio": 0.9908280751967735, 
        "total_count": 46119, 
        "javascript_template_head": "", 
        "codechecker_handle": "", 
        "migrated_resource": null, 
        "custom_tabs": null, 
        "cpp14_template_head": "", 
        "is_skip_band_challenge": false, 
        "public_test_cases": true, 
        "available_translations": [], 
        "cpp_template": "/*\n  Get Nth element from the end in a linked list of integers\n  Number of elements in the list will always be greater than N.\n  Node is defined as \n  struct Node\n  {\n     int data;\n     struct Node *next;\n  }\n*/\nint GetNode(Node *head,int positionFromTail)\n{\n  // This is a \"method-only\" submission. \n  // You only need to complete this method. \n}", 
        "is_preview_contest": false, 
        "cpp_template_tail": "", 
        "hacker": {
            "username": "HackerRank", 
            "is_admin": true, 
            "id": 15055, 
            "avatar": "https://hrcdn.net/s3_pub/hr-avatars/4c95f96b-1ff9-46ed-98f8-cb3cb4ed8834/150x150.png"
        }, 
        "can_be_viewed": true, 
        "submitted_hackers_count": 46119, 
        "public_solutions": true, 
        "deleted": false, 
        "real_dynamic": false, 
        "difficulty_score": "0.019", 
        "difficulty": 0.9859922178988327, 
        "active": true, 
        "slug": "get-the-value-of-the-node-at-a-specific-position-from-the-tail", 
        "show_skeliton": null, 
        "player_count": 2, 
        "is_editorial_available": true, 
        "epoch_endtime": null, 
        "cpp_template_head": "", 
        "author_avatar": "https://d3rpyts3de3lx8.cloudfront.net/hackerrank/assets/gravatar.jpg", 
        "judgebot_language": null, 
        "requirements_description": null, 
        "java_template": "/*\n  Get Nth element from the end in a linked list of integers\n  Number of elements in the list will always be greater than N.\n  Node is defined as \n  class Node {\n     int data;\n     Node next;\n  }\n*/\n    \nint GetNode(Node head,int n) {\n  \t// This is a \"method-only\" submission. \n  \t// You only need to complete this method. \n\n\n}", 
        "python_template": "#Body\n\"\"\"\n Get Node data of the Nth Node from the end.\n head could be None as well for empty list\n Node is defined as\n \n class Node(object):\n \n   def __init__(self, data=None, next_node=None):\n       self.data = data\n       self.next = next_node\n\n return back the node data of the linked list in the below method.\n\"\"\"\n\ndef GetNode(head, position):\n  \n  \n  \n  \n  \n  \n  \n  \n  \n  ", 
        "color": null, 
        "has_all_test_cases_public": false, 
        "time_left": null, 
        "cpp14_template": "/*\n  Get Nth element from the end in a linked list of integers\n  Number of elements in the list will always be greater than N.\n  Node is defined as \n  struct Node\n  {\n     int data;\n     struct Node *next;\n  }\n*/\nint GetNode(Node *head,int positionFromTail)\n{\n  // This is a \"method-only\" submission. \n  // You only need to complete this method. \n}", 
        "kind": "code", 
        "is_custom": false, 
        "solved_score": 0.5, 
        "expert_solution_status": false, 
        "custom": false, 
        "preview": "Given the head of a linked list, get the value of the node at a given position when counting backwards from the tail.", 
        "cpp14_template_tail": "", 
        "company": null, 
        "is_text": false, 
        "require_unlock": true, 
        "has_started": true, 
        "judgebot": null, 
        "custom_checker_language": null, 
        "custom_case": true, 
        "topics": [], 
        "updated_at": "2017-03-24T12:07:11.000Z", 
        "author_name": "harsha_s", 
        "onboarding": null, 
        "id": 1156, 
        "has_ended": false, 
        "javascript_template": "/*\n    Get Nth element data from the end in a Linked List\n    Number of elements in the list will always be greater than N.\n    Node is defined as\n    var Node = function(data) {\n        this.data = data;\n        this.next = null;\n    }\n*/\n\n// This is a \"method-only\" submission.\n// You only need to complete this method.\n\nfunction getNodeValue( head, position) {\n    \n}\n", 
        "is_solution_unlocked": false, 
        "checker_program": null, 
        "status": null, 
        "category": "ai", 
        "track": {
            "name": "Linked Lists", 
            "taxonomy": 1, 
            "track_slug": "data-structures", 
            "track_id": 17, 
            "track_name": "Data Structures", 
            "id": 39, 
            "rewards_system_enabled": null, 
            "slug": "linked-lists"
        }, 
        "javascript_template_tail": "", 
        "body_html": "<div class='challenge_problem_statement'><div class='msB challenge_problem_statement_body'><div class='hackdown-content'><style id=\"MathJax_SVG_styles\">.MathJax_SVG_Display {text-align: center; margin: 1em 0em; position: relative; display: block!important; text-indent: 0; max-width: none; max-height: none; min-width: 0; min-height: 0; width: 100%}\n.MathJax_SVG .MJX-monospace {font-family: monospace}\n.MathJax_SVG .MJX-sans-serif {font-family: sans-serif}\n.MathJax_SVG {display: inline; font-style: normal; font-weight: normal; line-height: normal; font-size: 100%; font-size-adjust: none; text-indent: 0; text-align: left; text-transform: none; letter-spacing: normal; word-spacing: normal; word-wrap: normal; white-space: nowrap; float: none; direction: ltr; max-width: none; max-height: none; min-width: 0; min-height: 0; border: 0; padding: 0; margin: 0}\n.MathJax_SVG * {transition: none; -webkit-transition: none; -moz-transition: none; -ms-transition: none; -o-transition: none}\n.mjx-svg-href {fill: blue; stroke: blue}\n</style><svg style=\"display: none;\"><defs id=\"MathJax_SVG_glyphs\"></defs></svg><p><sub>This challenge is part of a tutorial track by <a href=\"http://www.youtube.com/mycodeschool\">MyCodeSchool</a></sub></p>\n\n<p>You\u2019re given the pointer to the head node of a linked list and a specific position. Counting backwards from the tail node of the linked list, get the value of the node at the given position. A position of 0 corresponds to the tail, 1 corresponds to the node before the tail and so on.</p>\n\n<p><strong>Input Format</strong> <br>\nYou have to complete the <code>int GetNode(Node* head, int positionFromTail)</code> method which takes two arguments - the head of the linked list and the position of the node from the tail. positionFromTail will be at least 0 and less than the number of nodes in the list. You should NOT read any input from stdin/console.  </p>\n\n<p><strong>Constraints</strong> <br>\nPosition will be a valid element in linked list.  </p>\n\n<p><strong>Output Format</strong> <br>\nFind the node at the given position counting backwards from the tail. Then <code>return</code> the <code>data</code> contained in this node. Do NOT print anything to stdout/console.</p>\n\n<p><strong>Sample Input</strong>  </p>\n\n<pre><code>1 -&gt; 3 -&gt; 5 -&gt; 6 -&gt; NULL, positionFromTail = 0\n1 -&gt; 3 -&gt; 5 -&gt; 6 -&gt; NULL, positionFromTail = 2\n</code></pre>\n\n<p><strong>Sample Output</strong></p>\n\n<pre><code>6\n3\n</code></pre></div></div></div>", 
        "max_score": 5, 
        "user_score": 0, 
        "created_at": "2013-10-23T11:28:37.000Z", 
        "countdown_time": 0
    }
}